llama.py
aiconfig_extension_llama-0.0.2.dist-info/METADATA
aiconfig_extension_llama-0.0.2.dist-info/WHEEL
aiconfig_extension_llama-0.0.2.dist-info/top_level.txt
aiconfig_extension_llama-0.0.2.dist-info/RECORD
